[
  {
    "timestamp": "2026-04-02T15:43:45.645401",
    "title": "Only true fans will feel this \ud83d\ude31 #edit #shorts #4k #marvel",
    "video_id": "GqBxs_dMkUs",
    "drive_file": "gafurovedit_ed82976b634c49e2965c883c317c7d6a.mp4",
    "file_size_mb": 16.5
  },
  {
    "timestamp": "2026-04-03T05:55:16.021576",
    "title": "4K Quality at its peak \u2728 #lamborghini #4kedit #shorts",
    "video_id": "0tZXhcKiBMY",
    "drive_file": "gafurovedit_93a22f0925634875ae8ef35c47a29a10.mp4",
    "file_size_mb": 4.7
  }
]